aws_cost_explorer/__init__.py
aws_cost_explorer/main.py
aws_cost_explorer-0.1.1.dist-info/METADATA
aws_cost_explorer-0.1.1.dist-info/WHEEL
aws_cost_explorer-0.1.1.dist-info/entry_points.txt
aws_cost_explorer-0.1.1.dist-info/RECORD
