Metadata-Version: 2.3
Name: aws-cost-explorer
Version: 0.1.1
Summary: View aws costs from the CLI
Author-email: Michael Lingelbach <m.j.lbach@gmail.com>
Requires-Python: >=3.11
Requires-Dist: boto3
Requires-Dist: matplotlib
